architecture_as_code/__init__.py
architecture_as_code/templates/k8s_template.yaml
architecture_as_code/templates/k8s_template_ingress.yaml
architecture_as_code/templates/k8s_template_volume_claim.yaml
architecture_as_code/templates/k8s_template_volume_claim_tanzu.yaml
architecture_as_code-0.0.14.dist-info/LICENSE
architecture_as_code-0.0.14.dist-info/METADATA
architecture_as_code-0.0.14.dist-info/WHEEL
architecture_as_code-0.0.14.dist-info/top_level.txt
architecture_as_code-0.0.14.dist-info/RECORD
