Metadata-Version: 2.1
Name: architecture-as-code
Version: 0.0.14
Summary: Standardise and speed up application architecture design and deployments
Home-page: https://github.com/kg0809/architecture-as-code
Author: kg0809
Author-email: kg0809developer@gmail.com
License: UNKNOWN
Project-URL: Bug Tracker, https://github.com/kg0809/architecture-as-code/issues
Platform: UNKNOWN
Classifier: Programming Language :: Python :: 3
Classifier: License :: OSI Approved :: MIT License
Classifier: Operating System :: OS Independent
Requires-Python: >=3.6
Requires-Dist: ruamel.yaml
Requires-Dist: diagrams
Requires-Dist: redis
